redcapy/__init__.py
redcapy/error.py
redcapy/keywords.py
redcapy/metadata.py
redcapy/request.py
redcapy-0.4.1.dist-info/LICENSE
redcapy-0.4.1.dist-info/METADATA
redcapy-0.4.1.dist-info/WHEEL
redcapy-0.4.1.dist-info/top_level.txt
redcapy-0.4.1.dist-info/RECORD
