Metadata-Version: 2.1
Name: redcapy
Version: 0.4.1
Summary: Python package to access REDCAP API
Home-page: https://github.com/unaisaralegui/redcapy
Author: Unai Saralegui
Author-email: usaralegui@gmail.com
License: UNKNOWN
Platform: UNKNOWN
Classifier: Programming Language :: Python :: 3
Classifier: License :: OSI Approved :: MIT License
Classifier: Operating System :: OS Independent
Requires-Dist: requests
